LICENSE
MANIFEST.in
README.md
pyproject.toml
setup.py
tensornets/__init__.py
tensornets/capsulenets.py
tensornets/darknets.py
tensornets/densenets.py
tensornets/detections.py
tensornets/efficientnets.py
tensornets/inceptions.py
tensornets/layers.py
tensornets/middles.py
tensornets/mobilenets.py
tensornets/nasnets.py
tensornets/ops.py
tensornets/preprocess.py
tensornets/pretrained.py
tensornets/resnets.py
tensornets/squeezenets.py
tensornets/tnets.py
tensornets/unet.py
tensornets/utils.py
tensornets/version_utils.py
tensornets/vggs.py
tensornets/wavenets.py
tensornets/zf.py
tensornets.egg-info/PKG-INFO
tensornets.egg-info/SOURCES.txt
tensornets.egg-info/dependency_links.txt
tensornets.egg-info/top_level.txt
tensornets/contrib_framework/__init__.py
tensornets/contrib_framework/arg_scope.py
tensornets/contrib_framework/variables.py
tensornets/contrib_layers/__init__.py
tensornets/contrib_layers/initializers.py
tensornets/contrib_layers/layers.py
tensornets/contrib_layers/normalization.py
tensornets/contrib_layers/optimizers.py
tensornets/contrib_layers/regularizers.py
tensornets/contrib_layers/rev_block_lib.py
tensornets/contrib_layers/summaries.py
tensornets/contrib_layers/utils.py
tensornets/datasets/__init__.py
tensornets/datasets/coco.names
tensornets/datasets/coco.py
tensornets/datasets/imagenet.py
tensornets/datasets/voc.names
tensornets/datasets/voc.py
tensornets/references/__init__.py
tensornets/references/coco.names
tensornets/references/rcnns.py
tensornets/references/rpn_utils.py
tensornets/references/voc.names
tensornets/references/yolo_utils.py
tensornets/references/yolos.py
tensornets/references/darkflow_utils/__init__.py
tensornets/references/darkflow_utils/__init__.pyc
tensornets/references/darkflow_utils/box.py
tensornets/references/darkflow_utils/box.pyc
tensornets/references/darkflow_utils/get_boxes.c
tensornets/references/darkflow_utils/get_boxes.pyx
tensornets/references/darkflow_utils/get_boxes.so
tensornets/references/darkflow_utils/nms.c
tensornets/references/darkflow_utils/nms.pxd
tensornets/references/darkflow_utils/nms.pyx
tensornets/references/darkflow_utils/nms.so