Metadata-Version: 1.1
Name: tensornets
Version: 0.4.6
Summary: high level network definitions in tensorflow
Home-page: https://github.com/taehoonlee/tensornets
Author: Taehoon Lee
Author-email: me@taehoonlee.com
License: MIT
Download-URL: https://github.com/taehoonlee/tensornets/tarball/0.4.6
Platform: UNKNOWN
